<annotation><filename>001170.jpg</filename><folder>users/cakirogluozan//part13</folder><source><submittedBy>ozan çakıroğlu</submittedBy></source><imagesize><nrows>375</nrows><ncols>500</ncols></imagesize><object><name>face</name><deleted>0</deleted><verified>0</verified><occluded>no</occluded><attributes></attributes><parts><hasparts></hasparts><ispartof></ispartof></parts><date>16-Jul-2018 09:56:20</date><id>0</id><segm><username>anonymous</username><box><xmin>244</xmin><ymin>123</ymin><xmax>323</xmax><ymax>253</ymax></box><mask>001170_mask_0.png</mask><scribbles><xmin>236.5</xmin><ymin>118</ymin><xmax>323.5</xmax><ymax>268</ymax><scribble_name>001170_scribble_0.png</scribble_name></scribbles></segm></object><object><name>face</name><deleted>0</deleted><verified>0</verified><occluded>no</occluded><attributes></attributes><parts><hasparts></hasparts><ispartof></ispartof></parts><date>16-Jul-2018 09:56:47</date><id>1</id><segm><username>anonymous</username><box><xmin>322</xmin><ymin>142</ymin><xmax>412</xmax><ymax>257</ymax></box><mask>001170_mask_1.png</mask><scribbles><xmin>287.5</xmin><ymin>133</ymin><xmax>446.5</xmax><ymax>301</ymax><scribble_name>001170_scribble_1.png</scribble_name></scribbles></segm></object></annotation>