<annotation><filename>002235.jpg</filename><folder>users/cakirogluozan//part7</folder><source><submittedBy>ozan &#231;ak&#305;ro&#287;lu</submittedBy></source><imagesize><nrows>333</nrows><ncols>500</ncols></imagesize><object><name>face</name><deleted>0</deleted><verified>0</verified><occluded>no</occluded><attributes /><parts><hasparts /><ispartof /></parts><date>03-Apr-2018 14:57:10</date><id>0</id><segm><username>cakirogluozan</username><box><xmin>94</xmin><ymin>112</ymin><xmax>164</xmax><ymax>184</ymax></box><mask>002235_mask_0.png</mask><scribbles><xmin>78</xmin><ymin>95.5</ymin><xmax>174</xmax><ymax>212.5</ymax><scribble_name>002235_scribble_0.png</scribble_name></scribbles></segm></object><object><name>face</name><deleted>0</deleted><verified>0</verified><occluded>no</occluded><attributes /><parts><hasparts /><ispartof /></parts><date>03-Apr-2018 14:57:21</date><id>1</id><segm><username>cakirogluozan</username><box><xmin>199</xmin><ymin>116</ymin><xmax>259</xmax><ymax>201</ymax></box><mask>002235_mask_1.png</mask><scribbles><xmin>173.25</xmin><ymin>93.5</ymin><xmax>273.75</xmax><ymax>252.5</ymax><scribble_name>002235_scribble_1.png</scribble_name></scribbles></segm></object><object><name>face</name><deleted>0</deleted><verified>0</verified><occluded>no</occluded><attributes /><parts><hasparts /><ispartof /></parts><date>03-Apr-2018 14:57:48</date><id>2</id><segm><username>cakirogluozan</username><box><xmin>243</xmin><ymin>161</ymin><xmax>288</xmax><ymax>225</ymax></box><mask>002235_mask_2.png</mask><scribbles><xmin>182.5</xmin><ymin>144.75</ymin><xmax>305.5</xmax><ymax>248.25</ymax><scribble_name>002235_scribble_2.png</scribble_name></scribbles></segm></object><object><name>face</name><deleted>0</deleted><verified>0</verified><occluded>no</occluded><attributes /><parts><hasparts /><ispartof /></parts><date>03-Apr-2018 14:57:59</date><id>3</id><segm><username>cakirogluozan</username><box><xmin>295</xmin><ymin>135</ymin><xmax>350</xmax><ymax>194</ymax></box><mask>002235_mask_3.png</mask><scribbles><xmin>272.75</xmin><ymin>117.75</ymin><xmax>370.25</xmax><ymax>227.25</ymax><scribble_name>002235_scribble_3.png</scribble_name></scribbles></segm></object></annotation>