<annotation><filename>006163.jpg</filename><folder>users/celbirlik//cano</folder><source><submittedBy>can</submittedBy></source><imagesize><nrows>500</nrows><ncols>357</ncols></imagesize><object><name>face</name><deleted>0</deleted><verified>0</verified><occluded>no</occluded><attributes></attributes><parts><hasparts></hasparts><ispartof></ispartof></parts><date>05-Oct-2018 12:47:25</date><id>0</id><segm><username>anonymous</username><box><xmin>151</xmin><ymin>124</ymin><xmax>205</xmax><ymax>183</ymax></box><mask>006163_mask_0.png</mask><scribbles><xmin>125</xmin><ymin>108.75</ymin><xmax>239</xmax><ymax>212.25</ymax><scribble_name>006163_scribble_0.png</scribble_name></scribbles></segm></object></annotation>