<annotation><filename>006948.jpg</filename><folder>users/celbirlik//cano</folder><source><submittedBy>can</submittedBy></source><imagesize><nrows>375</nrows><ncols>500</ncols></imagesize><object><name>face</name><deleted>0</deleted><verified>0</verified><occluded>no</occluded><attributes></attributes><parts><hasparts></hasparts><ispartof></ispartof></parts><date>05-Oct-2018 14:48:50</date><id>0</id><segm><username>anonymous</username><box><xmin>264</xmin><ymin>48</ymin><xmax>391</xmax><ymax>249</ymax></box><mask>006948_mask_0.png</mask><scribbles><xmin>247.25</xmin><ymin>0</ymin><xmax>407.75</xmax><ymax>312.5</ymax><scribble_name>006948_scribble_0.png</scribble_name></scribbles></segm></object><object><name>face</name><deleted>0</deleted><verified>0</verified><occluded>no</occluded><attributes></attributes><parts><hasparts></hasparts><ispartof></ispartof></parts><date>05-Oct-2018 14:49:04</date><id>1</id><segm><username>anonymous</username><box><xmin>9</xmin><ymin>85</ymin><xmax>112</xmax><ymax>239</ymax></box><mask>006948_mask_1.png</mask><scribbles><xmin>0</xmin><ymin>70.5</ymin><xmax>125.75</xmax><ymax>241.5</ymax><scribble_name>006948_scribble_1.png</scribble_name></scribbles></segm></object></annotation>