<annotation><filename>007817.jpg</filename><folder>users/celbirlik//haqo</folder><source><submittedBy>can</submittedBy></source><imagesize><nrows>500</nrows><ncols>474</ncols></imagesize><object><name>face</name><deleted>0</deleted><verified>0</verified><occluded>no</occluded><attributes></attributes><parts><hasparts></hasparts><ispartof></ispartof></parts><date>05-Oct-2018 13:23:33</date><id>0</id><segm><username>anonymous</username><box><xmin>105</xmin><ymin>64</ymin><xmax>229</xmax><ymax>229</ymax></box><mask>007817_mask_0.png</mask><scribbles><xmin>76.5</xmin><ymin>0</ymin><xmax>277.5</xmax><ymax>281.5</ymax><scribble_name>007817_scribble_0.png</scribble_name></scribbles></segm></object><object><name>face</name><deleted>0</deleted><verified>0</verified><occluded>no</occluded><attributes></attributes><parts><hasparts></hasparts><ispartof></ispartof></parts><date>05-Oct-2018 13:23:50</date><id>1</id><segm><username>anonymous</username><box><xmin>241</xmin><ymin>107</ymin><xmax>350</xmax><ymax>250</ymax></box><mask>007817_mask_1.png</mask><scribbles><xmin>207.5</xmin><ymin>84.75</ymin><xmax>384.5</xmax><ymax>290.25</ymax><scribble_name>007817_scribble_1.png</scribble_name></scribbles></segm></object></annotation>