<annotation><filename>001417.jpg</filename><folder>users/cakirogluozan//part2</folder><source><submittedBy>ozan &#231;ak&#305;ro&#287;lu</submittedBy></source><imagesize><nrows>396</nrows><ncols>480</ncols></imagesize><object><name>face</name><deleted>0</deleted><verified>0</verified><occluded>no</occluded><attributes /><parts><hasparts /><ispartof /></parts><date>02-Apr-2018 16:57:20</date><id>0</id><segm><username>anonymous</username><box><xmin>261</xmin><ymin>66</ymin><xmax>284</xmax><ymax>82</ymax></box><mask>001417_mask_0.png</mask><scribbles><xmin>255</xmin><ymin>53.75</ymin><xmax>297</xmax><ymax>91.25</ymax><scribble_name>001417_scribble_0.png</scribble_name></scribbles></segm></object></annotation>