<annotation><filename>007582.jpg</filename><folder>users/celbirlik//haqo</folder><source><submittedBy>can</submittedBy></source><imagesize><nrows>500</nrows><ncols>333</ncols></imagesize><object><name>face</name><deleted>0</deleted><verified>0</verified><occluded>no</occluded><attributes></attributes><parts><hasparts></hasparts><ispartof></ispartof></parts><date>05-Oct-2018 13:01:56</date><id>0</id><segm><username>anonymous</username><box><xmin>107</xmin><ymin>47</ymin><xmax>209</xmax><ymax>162</ymax></box><mask>007582_mask_0.png</mask><scribbles><xmin>98.75</xmin><ymin>31</ymin><xmax>214.25</xmax><ymax>181</ymax><scribble_name>007582_scribble_0.png</scribble_name></scribbles></segm></object></annotation>