<annotation><filename>008041.jpg</filename><folder>users/celbirlik//haqo</folder><source><submittedBy>can</submittedBy></source><imagesize><nrows>500</nrows><ncols>375</ncols></imagesize><object><name>face</name><deleted>0</deleted><verified>0</verified><occluded>no</occluded><attributes></attributes><parts><hasparts></hasparts><ispartof></ispartof></parts><date>05-Oct-2018 14:13:56</date><id>0</id><segm><username>celbirlik</username><box><xmin>100</xmin><ymin>168</ymin><xmax>214</xmax><ymax>291</ymax></box><mask>008041_mask_0.png</mask><scribbles><xmin>70.75</xmin><ymin>164.75</ymin><xmax>234.25</xmax><ymax>292.25</ymax><scribble_name>008041_scribble_0.png</scribble_name></scribbles></segm></object></annotation>